{"status":"success","tp":1,"msg":"Cities fetched successfully.","result":{"\"124687\"":"Aneby","\"124660\"":"Bankeryd","\"124636\"":"Bodafors","\"124631\"":"Bor","\"124620\"":"Bredaryd","\"124591\"":"Ekenassjon","\"124588\"":"Eksjoe","\"124566\"":"Forserum","\"124564\"":"Forsheda","\"124545\"":"Gislaved","\"124541\"":"Gnosjoe","\"124536\"":"Graenna","\"124526\"":"Habo","\"124495\"":"Hestra","\"124494\"":"Hillerstorp","\"124467\"":"Huskvarna","\"124450\"":"Jonkoping","\"124433\"":"Kaxholmen","\"124392\"":"Landsbro","\"124351\"":"Malmback","\"124345\"":"Mariannelund","\"124343\"":"Marieholm","\"124318\"":"Mullsjoe","\"124312\"":"Nassjo","\"124288\"":"Odensjo","\"124250\"":"Reftele","\"124238\"":"Rydaholm","\"124224\"":"Saevsjoe","\"124208\"":"Skillingaryd","\"124194\"":"Smalandsstenar","\"124163\"":"Stockaryd","\"124131\"":"Taberg","\"124126\"":"Tenhult","\"124108\"":"Tranas","\"124088\"":"Vaggeryd","\"124072\"":"Varnamo","\"124059\"":"Vetlanda","\"124042\"":"Vrigstad"},"hits":"5163"}