{"status":"success","tp":1,"msg":"Cities fetched successfully.","result":{"\"94654\"":"Azemmour","\"94649\"":"Berrechid","\"94641\"":"Boulaouane","\"94638\"":"Bouskoura","\"94637\"":"Bouznika","\"94634\"":"Casablanca","\"94630\"":"Dar Bouazza","\"94620\"":"El Jadida","\"94605\"":"Guisser","\"94575\"":"Mediouna","\"94685\"":"Mellila","\"94570\"":"Mohammedia","\"94569\"":"Moulay Abdallah","\"94604\"":"Oulad Frej","\"94628\"":"Riah","\"94540\"":"Settat","\"94537\"":"Sidi Bennour","\"94525\"":"Sidi Smai'il","\"94474\"":"Tit Mellil"},"hits":"4068"}