{"status":"success","tp":1,"msg":"Cities fetched successfully.","result":{"\"114337\"":"Bras-Panon","\"114336\"":"Cilaos","\"114335\"":"L'Entre-Deux","\"114334\"":"La Possession","\"114333\"":"Le Port","\"114331\"":"Le Tampon","\"114332\"":"Les Avirons","\"114330\"":"Petite-Ile","\"114338\"":"Piton Saint-Leu","\"114329\"":"Saint-Andre","\"114328\"":"Saint-Benoit","\"114327\"":"Saint-Denis","\"114323\"":"Saint-Joseph","\"114322\"":"Saint-Leu","\"114321\"":"Saint-Louis","\"114320\"":"Saint-Paul","\"114319\"":"Saint-Philippe","\"114318\"":"Saint-Pierre","\"114326\"":"Sainte-Marie","\"114325\"":"Sainte-Rose","\"114324\"":"Sainte-Suzanne","\"114317\"":"Salazie","\"114316\"":"Trois-Bassins"},"hits":"4521"}