{"status":"success","tp":1,"msg":"Cities fetched successfully.","result":{"\"130653\"":"Chornukhy","\"130625\"":"Chutove","\"130613\"":"Dykan'ka","\"130553\"":"Hadyach","\"130545\"":"Hlobyne","\"130523\"":"Hradyz'k","\"130522\"":"Hrebinka","\"130462\"":"Kamennyye Potoki","\"130451\"":"Karlivka","\"130433\"":"Khorol","\"130409\"":"Kobelyaky","\"130842\"":"Komsomolsk","\"130457\"":"Komyshnya","\"130365\"":"Kotel'va","\"130359\"":"Kozel'shchyna","\"130325\"":"Kremenchuk","\"130265\"":"Lokhvytsya","\"130258\"":"Lubny","\"130251\"":"Lutovynivka","\"130207\"":"Mashivka","\"130177\"":"Myrhorod","\"130069\"":"Novi Sanzhary","\"130040\"":"Oposhnya","\"130033\"":"Orzhytsya","\"129957\"":"Poltava","\"129982\"":"Pyryatyn","\"129908\"":"Reshetylivka","\"129898\"":"Romodan","\"129859\"":"Semenivka","\"129854\"":"Sencha","\"129824\"":"Shyshaky","\"129619\"":"Velyka Bahachka","\"129610\"":"Velyki Sorochyntsi","\"129479\"":"Zin'kiv"},"hits":"5487"}