{"status":"success","tp":1,"msg":"Cities fetched successfully.","result":{"\"101810\"":"Demsa","\"101758\"":"Fufore","\"101745\"":"Ganye","\"101731\"":"Gella","\"101726\"":"Girei","\"101723\"":"Gombi","\"101715\"":"Gulak","\"101709\"":"Guyuk","\"101694\"":"Holma","\"101693\"":"Hong","\"101584\"":"Jada","\"101572\"":"Jimeta","\"101489\"":"Lamurde","\"101481\"":"Madagali","\"101470\"":"Maiha","\"101452\"":"Mayo-Belwa","\"101447\"":"Michika","\"101433\"":"Mubi","\"101418\"":"Ngurore","\"101406\"":"Numan","\"101264\"":"Shelleng","\"101256\"":"Song","\"101236\"":"Toungo","\"101184\"":"Yola"},"hits":"4207"}