{"status":"success","tp":1,"msg":"Cities fetched successfully.","result":{"\"27272\"":"Adligenswil","\"27257\"":"Altishofen","\"27214\"":"Ballwil","\"27186\"":"Beromuenster","\"27134\"":"Buchrain","\"27123\"":"Bueron","\"27118\"":"Buttisholz","\"27053\"":"Dagmersellen","\"27025\"":"Ebikon","\"27014\"":"Eich","\"27008\"":"Emmen","\"27003\"":"Entlebuch","\"26989\"":"Escholzmatt","\"26986\"":"Ettiswil","\"26967\"":"Fluehli","\"26938\"":"Geuensee","\"26899\"":"Grosswangen","\"26892\"":"Gunzwil","\"26886\"":"Hasle","\"26870\"":"Hildisrieden","\"26863\"":"Hitzkirch","\"26862\"":"Hochdorf","\"26860\"":"Hohenrain","\"26853\"":"Horw","\"26842\"":"Inwil","\"26815\"":"Knutwil","\"26805\"":"Kriens","\"26745\"":"Littau","\"26733\"":"Luthern","\"26728\"":"Luzern","\"26719\"":"Malters","\"26706\"":"Mauensee","\"26705\"":"Meggen","\"26704\"":"Meierskappel","\"26692\"":"Menznau","\"26647\"":"Nebikon","\"26643\"":"Neudorf","\"26641\"":"Neuenkirch","\"26628\"":"Nottwil","\"26611\"":"Oberkirch","\"26570\"":"Pfaffnau","\"26535\"":"Reiden","\"26511\"":"Roemerswil","\"26509\"":"Root","\"26492\"":"Ruswil","\"26447\"":"Schenkon","\"26435\"":"Schoetz","\"26432\"":"Schuepfheim","\"26429\"":"Schwarzenberg","\"26416\"":"Sempach","\"26374\"":"Sursee","\"26347\"":"Triengen","\"26335\"":"Udligenswil","\"26280\"":"Vitznau","\"26254\"":"Wauwil","\"26251\"":"Weggis","\"26246\"":"Werthenstein","\"26239\"":"Wikon","\"26233\"":"Willisau","\"26221\"":"Wolhusen","\"26209\"":"Zell"},"hits":"5178"}