{"status":"success","tp":1,"msg":"Cities fetched successfully.","result":{"\"65136\"":"Ahoghill","\"65090\"":"Annahilt","\"65089\"":"Annalong","\"65083\"":"Antrim","\"65076\"":"Ardglass","\"65071\"":"Armagh","\"65006\"":"Ballinamallard","\"65003\"":"Ballycastle","\"65002\"":"Ballyclare","\"65001\"":"Ballygowan","\"65000\"":"Ballykelly","\"64999\"":"Ballymena","\"64998\"":"Ballymoney","\"64997\"":"Ballynahinch","\"64996\"":"Ballywalter","\"64990\"":"Banbridge","\"64985\"":"Bangor","\"64918\"":"Belfast","\"64916\"":"Bellaghy","\"65221\"":"Craigavon","\"65360\"":"Newcastle"},"hits":"5513"}