{"status":"success","tp":1,"msg":"Cities fetched successfully.","result":{"\"93765\"":"Bakanas","\"93714\"":"Balpyk Bi","\"93748\"":"Burunday","\"93741\"":"Dostyq","\"93725\"":"Esik","\"93669\"":"Kapshagay","\"93718\"":"Kegen","\"93695\"":"Lepsy","\"93690\"":"Matay","\"93737\"":"Otegen Batyra","\"93673\"":"Pervomayskiy","\"93657\"":"Sarkand","\"93654\"":"Saryozek","\"93635\"":"Taldykorgan","\"93636\"":"Taldyqorghan","\"93634\"":"Talghar","\"93630\"":"Tekeli","\"93621\"":"Turgen","\"93803\"":"Ulken","\"93618\"":"Ush-Tyube","\"93675\"":"Zharkent"},"hits":"3299"}