{"status":"success","tp":1,"msg":"Cities fetched successfully.","result":{"\"68904\"":"Abadszalok","\"68899\"":"Alattyan","\"68873\"":"Besenyszog","\"68863\"":"Cibakhaza","\"68857\"":"Cserkeszolo","\"68830\"":"Fegyvernek","\"68794\"":"Janoshida","\"68792\"":"Jaszalsoszentgyorgy","\"68791\"":"Jaszapati","\"69215\"":"Jaszarokszallas","\"69214\"":"Jaszbereny","\"68790\"":"Jaszdozsa","\"68789\"":"Jaszjakohalma","\"68787\"":"Jaszkiser","\"68786\"":"Jaszladany","\"68785\"":"Jaszszentandras","\"68778\"":"Karcag","\"68772\"":"Kenderes","\"68771\"":"Kengyel","\"68765\"":"Kisujszallas","\"68753\"":"Kunhegyes","\"68752\"":"Kunmadaras","\"68751\"":"Kunszentmarton","\"68727\"":"Mezotur","\"68689\"":"Ocsod","\"68664\"":"Rakoczifalva","\"68663\"":"Rakocziujfalu","\"68642\"":"Szajol","\"69438\"":"Szeleveny","\"68625\"":"Szolnok","\"68614\"":"Tiszabo","\"68613\"":"Tiszabura","\"68608\"":"Tiszafoldvar","\"68607\"":"Tiszafured","\"68599\"":"Tiszapuspoki","\"68598\"":"Tiszaroff","\"68597\"":"Tiszasuly","\"68596\"":"Tiszaszentimre","\"69443\"":"Tiszaszolos","\"68589\"":"Torokszentmiklos","\"68588\"":"Toszeg","\"68585\"":"Turkeve","\"68580\"":"Ujszasz","\"68574\"":"Zagyvarekas"},"hits":"2866"}