{"status":"success","tp":1,"msg":"Cities fetched successfully.","result":{"\"12266\"":"'Ahuimanu","\"12265\"":"'Aiea","\"12243\"":"'Ele'ele","\"12244\"":"'Ewa Beach","\"12245\"":"'Ewa Gentry","\"12246\"":"'Ewa Villages","\"12210\"":"'Oma'o","\"185077\"":"Ahuimanu","\"185078\"":"Aiea","\"12271\"":"Ainaloa","\"12272\"":"Anahola","\"12273\"":"Captain Cook","\"185079\"":"Ewa Beach","\"12247\"":"Fern Acres","\"12625\"":"Haiku-Pauwela","\"12248\"":"Halawa","\"12249\"":"Halawa Heights","\"12250\"":"Hale'iwa","\"12251\"":"Hana","\"12252\"":"Hanama'ulu","\"12253\"":"Hanapepe","\"12254\"":"Hanapepe Heights","\"12255\"":"Hau'ula","\"12257\"":"Hawaiian Acres","\"12256\"":"Hawaiian Beaches","\"12259\"":"Hawaiian Ocean View","\"12258\"":"Hawaiian Paradise Park","\"12260\"":"Hawi","\"12261\"":"He'eia","\"12626\"":"Hickam Field","\"15634\"":"Hilo","\"12262\"":"Holualoa","\"12263\"":"Honalo","\"12627\"":"Honaunau-Napoopoo","\"12264\"":"Honoka'a","\"12717\"":"Honolulu","\"12267\"":"Iroquois Point","\"12268\"":"Ka'a'awa","\"12269\"":"Ka'anapali","\"12270\"":"Kaanapali Landing","\"12172\"":"Kahalu'u","\"12628\"":"Kahaluu-Keauhou","\"12173\"":"Kahuku","\"12174\"":"Kahului","\"12175\"":"Kailua","\"12176\"":"Kailua-Kona","\"12177\"":"Kalaheo","\"12178\"":"Kalaoa","\"12179\"":"Kaneohe","\"12180\"":"Kapa'a","\"185080\"":"Kapaa","\"12181\"":"Kapaau","\"12182\"":"Kaunakakai","\"12183\"":"Kea'au","\"12184\"":"Kealakekua","\"12185\"":"Kekaha","\"12186\"":"Keokea","\"12187\"":"Kihei","\"12188\"":"Kilauea","\"12189\"":"Koloa","\"12190\"":"Kualapu'u","\"12191\"":"Kurtistown","\"12193\"":"La'ie","\"12192\"":"Lahaina","\"12194\"":"Lanai City","\"12195\"":"Lawai","\"12197\"":"Leilani Estates","\"12196\"":"Leilani Estates","\"15632\"":"Lihue","\"12198\"":"Ma'ili","\"12199\"":"Makaha","\"12200\"":"Makaha Valley","\"12630\"":"Makakilo","\"12201\"":"Makakilo City","\"12202\"":"Makawao","\"12629\"":"Marine Corps Base Hawaii - MCBH","\"12203\"":"Maunawili","\"12204\"":"Mililani Town","\"12205\"":"Mokuleia","\"12206\"":"Mountain View","\"12207\"":"Nanakuli","\"12209\"":"Nanawale Estates","\"12208\"":"Nanawale Estates","\"12631\"":"Napili-Honokowai","\"12211\"":"Orchidlands Estates","\"12212\"":"Pahala","\"12213\"":"Paia","\"12214\"":"Papa'ikou","\"12215\"":"Pearl City","\"12216\"":"Pepeekeo","\"12217\"":"Princeville","\"12218\"":"Puhi","\"12219\"":"Pukalani","\"12220\"":"Punalu'u","\"12221\"":"Punaluu","\"12222\"":"Pupukea","\"12633\"":"Royal Kunia","\"12632\"":"Schofield Barracks","\"12223\"":"Village Park","\"12224\"":"Volcano","\"12225\"":"Wahiawa","\"12226\"":"Waialua","\"12227\"":"Waialua","\"12228\"":"Waianae","\"12634\"":"Waihee-Waiehu","\"12229\"":"Waikapu","\"12230\"":"Waikoloa","\"12231\"":"Waikoloa Village","\"12232\"":"Wailua","\"12233\"":"Wailua","\"12635\"":"Wailua Homesteads","\"15633\"":"Wailuku","\"12234\"":"Waimalu","\"15645\"":"Waimanalo","\"12235\"":"Waimanalo Beach","\"12236\"":"Waimea","\"12237\"":"Waimea","\"12238\"":"Wainaku","\"12239\"":"Waipahu","\"12241\"":"Waipi'o Acres","\"12240\"":"Waipio","\"12242\"":"Whitmore Village"},"hits":"5527"}