{"status":"success","tp":1,"msg":"Cities fetched successfully.","result":{"\"38451\"":"Caibarien","\"38449\"":"Calabazar de Sagua","\"38445\"":"Camajuani","\"38434\"":"Cifuentes","\"38427\"":"Corralillo","\"38421\"":"Encrucijada","\"38419\"":"Esperanza","\"38376\"":"Manicaragua","\"38351\"":"Placetas","\"38348\"":"Quemado de Guines","\"38345\"":"Rancho Veloz","\"38344\"":"Ranchuelo","\"38342\"":"Remedios","\"38337\"":"Sagua la Grande","\"38325\"":"Santa Clara","\"38320\"":"Santo Domingo"},"hits":"2385"}