{"status":"success","tp":1,"msg":"Cities fetched successfully.","result":{"\"21341\"":"Amirdzhan","\"21358\"":"Badamdar","\"21352\"":"Bakixanov","\"21337\"":"Baku","\"21335\"":"Balakhani","\"21336\"":"Bilajari","\"21330\"":"Bilajer","\"21328\"":"Binagadi","\"21329\"":"Biny Selo","\"21327\"":"Buzovna","\"21311\"":"Hovsan","\"21296\"":"Khodzhi-Gasan","\"21297\"":"Korgoz","\"21289\"":"Lokbatan","\"21286\"":"Mardakan","\"21285\"":"Mastaga","\"21282\"":"Nardaran","\"21340\"":"Pirallahi","\"21278\"":"Puta","\"21304\"":"Qala","\"21260\"":"Qaracuxur","\"21272\"":"Qobustan","\"21357\"":"Ramana","\"21268\"":"Sabuncu","\"21254\"":"Turkan","\"21308\"":"Yeni Suraxani","\"21246\"":"Zabrat","\"21243\"":"Zyrya"},"hits":"1899"}