{"status":"success","tp":1,"msg":"Cities fetched successfully.","result":{"\"38107\"":"Algarrobo","\"38085\"":"Aracataca","\"38025\"":"Buenavista","\"38007\"":"Calamar","\"37974\"":"Cerro de San Antonio","\"37954\"":"Chivolo","\"37950\"":"Cienaga","\"37934\"":"Concordia","\"37894\"":"El Banco","\"37873\"":"El Penon","\"37872\"":"El Pinon","\"37871\"":"El Reten","\"37841\"":"Fundacion","\"37804\"":"Guamal","\"37636\"":"Nueva Granada","\"37598\"":"Pedraza","\"37587\"":"Pijino","\"37582\"":"Pivijay","\"38162\"":"Plato","\"37565\"":"Puebloviejo","\"37528\"":"Remolino","\"37497\"":"Salamina","\"37484\"":"San Antonio","\"37434\"":"Santa Ana","\"37428\"":"Santa Marta","\"37254\"":"Zambrano"},"hits":"2330"}