{"status":"success","tp":1,"msg":"States fetched successfully.","result":{"\"9782164\"":"Andreas","\"9782165\"":"Arbory","\"9782166\"":"Ballaugh","\"9782167\"":"Braddan","\"9782168\"":"Bride","\"9782169\"":"Castletown","\"9782170\"":"Douglas","\"9782171\"":"German","\"9782172\"":"Jurby","\"9782173\"":"Laxey","\"9782176\"":"Lezayre","\"9782180\"":"Lonan","\"9782182\"":"Malew","\"9782183\"":"Marown","\"9782184\"":"Maughold","\"9782185\"":"Michael","\"9782186\"":"Onchan","\"9782187\"":"Patrick","\"9782188\"":"Peel","\"9782189\"":"Port Erin","\"9782190\"":"Port St Mary","\"9782191\"":"Ramsey","\"9782192\"":"Rushen","\"9782193\"":"Santon"},"hits":"1217"}