{"status":"success","tp":1,"msg":"Cities fetched successfully.","result":{"\"39865\"":"Albrechtice","\"39859\"":"Bartosovice","\"39858\"":"Baska","\"39823\"":"Bohumin","\"39817\"":"Bolatice","\"39787\"":"Bridlicna","\"39778\"":"Bruntal","\"39777\"":"Brusperk","\"39773\"":"Budisov nad Budisovkou","\"39763\"":"Bystrice","\"39752\"":"Celadna","\"39724\"":"Cesky Tesin","\"39711\"":"Chotebuz","\"39680\"":"Detmarovice","\"39677\"":"Dobra","\"39662\"":"Dolni Benesov","\"39633\"":"Dolni Zivotice","\"39609\"":"Frenstat pod Radhostem","\"39608\"":"Frycovice","\"39607\"":"Frydek-Mistek","\"39605\"":"Frydlant nad Ostravici","\"39602\"":"Fulnek","\"39597\"":"Haj ve Slezsku","\"39590\"":"Havirov","\"39578\"":"Hlucin","\"39570\"":"Hodslavice","\"39560\"":"Horni Benesov","\"39523\"":"Hradec nad Moravici","\"39501\"":"Hukvaldy","\"39486\"":"Jablunkov","\"39484\"":"Jakartovice","\"39451\"":"Jistebnik","\"39433\"":"Karvina","\"39418\"":"Klimkovice","\"39411\"":"Koberice","\"39404\"":"Komorni Lhotka","\"39401\"":"Koprivnice","\"39374\"":"Kravare","\"39366\"":"Krmelin","\"39365\"":"Krnov","\"39318\"":"Lichnov (o. Novy Jicin)","\"39870\"":"Lucina","\"39284\"":"Ludgerovice","\"39261\"":"Markvartovice","\"39247\"":"Mesto Albrechtice","\"39244\"":"Metylovice","\"39213\"":"Mokre Lazce","\"39201\"":"Morkov","\"39197\"":"Mosty u Jablunkova","\"39145\"":"Novy Jicin","\"39142\"":"Nydek","\"39135\"":"Odry","\"39130\"":"Oldrisov","\"39121\"":"Opava","\"39118\"":"Orlova","\"39108\"":"Ostrava","\"39107\"":"Ostravice","\"39100\"":"Otice","\"39096\"":"Palkovice","\"39093\"":"Paskov","\"39082\"":"Petrovice u Karvine","\"39081\"":"Petrvald","\"39037\"":"Prazmo","\"39029\"":"Pribor","\"38889\"":"Stare Mesto","\"38884\"":"Stary Bohumin","\"38798\"":"Trinec","\"38736\"":"Velka Polom","\"38732\"":"Velke Heraltice","\"38731\"":"Velke Hostice","\"38712\"":"Vendryne"},"hits":"2412"}